MANIFEST.in
README.rst
requirements.txt
setup.cfg
setup.py
src/django_pascal_templates.egg-info/PKG-INFO
src/django_pascal_templates.egg-info/SOURCES.txt
src/django_pascal_templates.egg-info/dependency_links.txt
src/django_pascal_templates.egg-info/requires.txt
src/django_pascal_templates.egg-info/top_level.txt
src/pascal_templates/__init__.py
src/pascal_templates/tests.py
src/pascal_templates/views.py